adafruit_ov7670.py
adafruit_circuitpython_ov7670-1.1.7.dist-info/licenses/LICENSE
adafruit_circuitpython_ov7670-1.1.7.dist-info/METADATA
adafruit_circuitpython_ov7670-1.1.7.dist-info/WHEEL
adafruit_circuitpython_ov7670-1.1.7.dist-info/top_level.txt
adafruit_circuitpython_ov7670-1.1.7.dist-info/RECORD
